py_ape/__init__.py
py_ape/ape_func.py
py_ape/main.py
py_ape-0.0.6.dist-info/LICENSE
py_ape-0.0.6.dist-info/METADATA
py_ape-0.0.6.dist-info/WHEEL
py_ape-0.0.6.dist-info/top_level.txt
py_ape-0.0.6.dist-info/RECORD
