Metadata-Version: 2.1
Name: py-ape
Version: 0.0.6
Summary: A small package for handling matching data based on BigGorilla package
Home-page: https://github.com/vietpq/py_ape
Author: VietPQ,ToiNV,NganNTB
Author-email: viet20304@gmail.com,dreamsimple2100@gmail.com,nganntb@hufi.edu.vn
License: UNKNOWN
Platform: UNKNOWN
Classifier: Programming Language :: Python :: 2
Classifier: License :: OSI Approved :: MIT License
Classifier: Operating System :: OS Independent
Requires-Python: >=2.7
Requires-Dist: pandas (==0.25.1)
Requires-Dist: numpy (==1.16.2)
Requires-Dist: scikit-learn (==0.19.1)
Requires-Dist: flexmatcher
Requires-Dist: py-stringsimjoin
Requires-Dist: py-stringmatching
Requires-Dist: py-entitymatching
Requires-Dist: tqdm
Requires-Dist: beautifulsoup4
